Workbook

Sheet Sommaire
A1: DR ÉLECTRIQUE INC. — SOMMAIRE D'ESTIMATION
A2: Bibliothèque Georgette-Lepage (Brossard) — Technologie RFID — aménagement RDC et étage
A3: Appel d'offres SP-GTER-26-0080 — Plans HF Experts-Conseils 26-29, émis pour AO 2026-09-16
B5: PARAMÈTRES
B6: Taux main-d'œuvre ($/h) — référence Jo | C6: 124
B7: Frais généraux / administration (%) — À FOURNIR PAR JO
B8: Profit (%) — À FOURNIR PAR JO
B9: Sous-traitance JCI/Simplex (AI) — prix à obtenir
B10: Sous-traitance parasismique — prix à obtenir (si incluse)
A12: Section | B12: Description | C12: Matériel | D12: Heures | E12: Main-d'œuvre | F12: Total
A13: A | B13: DÉMANTÈLEMENT / RELOCALISATION / TRAVAUX TEMPORAIRES | C13: =Détail!G19 -> 0 | D13: =Détail!I19 -> 124.3 | E13: =Détail!J19 -> 15413.2 | F13: =C13+E13 -> 15413.2
A14: B | B14: DISTRIBUTION / PANNEAUX | C14: =Détail!G31 -> 0 | D14: =Détail!I31 -> 45 | E14: =Détail!J31 -> 5580 | F14: =C14+E14 -> 5580
A15: C | B15: RACCORDEMENTS MÉCANIQUES | C15: =Détail!G42 -> 0 | D15: =Détail!I42 -> 66.8 | E15: =Détail!J42 -> 8283.2 | F15: =C15+E15 -> 8283.2
A16: D | B16: SERVICES — REZ-DE-CHAUSSÉE (E-104) | C16: =Détail!G61 -> 0 | D16: =Détail!I61 -> 211.1 | E16: =Détail!J61 -> 26176.4 | F16: =C16+E16 -> 26176.4
A17: E | B17: SERVICES — ÉTAGE (E-105) | C17: =Détail!G75 -> 0 | D17: =Détail!I75 -> 81.75 | E17: =Détail!J75 -> 10137 | F17: =C17+E17 -> 10137
A18: F | B18: ÉCLAIRAGE ET ÉCLAIRAGE D'URGENCE — RDC (E-203) | C18: =Détail!G88 -> 0 | D18: =Détail!I88 -> 101.98 | E18: =Détail!J88 -> 12645.52 | F18: =C18+E18 -> 12645.52
A19: G | B19: ALARME INCENDIE (travaux par l'électricien — note 4 E-201) | C19: =Détail!G98 -> 0 | D19: =Détail!I98 -> 32.6 | E19: =Détail!J98 -> 4042.4 | F19: =C19+E19 -> 4042.4
A20: H | B20: FRAIS DE CHANTIER / GÉNÉRAUX | C20: =Détail!G105 -> 0 | D20: =Détail!I105 -> 56 | E20: =Détail!J105 -> 6944 | F20: =C20+E20 -> 6944
B22: Coût direct (matériel + MO) | C22: =SUM(C13:C20) -> 0 | D22: =SUM(D13:D20) -> 719.53 | E22: =SUM(E13:E20) -> 89221.72 | F22: =SUM(F13:F20) -> 89221.72
B23: Matériel conduits/filage/dispositifs (liste Lumen) + sous-traitance (JCI + parasismique) | F23: ='Matériel Lumen'!F49+C9+C10 -> 23159.671
B24: Frais généraux | F24: =(F22+F23)*C7 -> 0
B25: Profit | F25: =(F22+F23+F24)*C8 -> 0
B26: PRIX TOTAL AVANT TAXES | F26: =SUM(F22:F25) -> 112381.39
B27: Jours-personne (8 h) | D27: =D22/8 -> 89.94125
B29: NOTES
B30: 1. Quantités relevées sur plans E-101 à E-502 (HF Experts-Conseils, émis AO 2026-09-16) — relevé préliminaire, à valider sur plans papier/échelle.
B31: 2. Longueurs de conduits/fils = HYPOTHÈSES (30 m/course RDC, 25 m/course étage, 8 m/point éclairage) — tracé exact à valider dans l'entreplafond du niveau inférieur (note 5 E-104).
B32: 3. Heures unitaires = estimé Léna AI (taux de productivité typiques commercial) — à valider par Jo.
B33: 4. Prix matériel : AUCUN prix inscrit — à obtenir (Guillevin / Westburne / Nedco / Wesco), prix réguliers.
B34: 5. Marges (FG + profit) : non assumées — à inscrire par Jo en C7/C8.
B35: 6. Contradictions relevées : UTA-1 disj. 40A (E-502) vs MOCP 35A (E-009); câblage data devis 36.1 vs « réutiliser câble existant » (E-104); schéma AI montre 2 détecteurs neufs à l'étage, plans montrent 2 neufs au RDC (plans prévalent).

Sheet Détail
A1: DR ÉLECTRIQUE INC. — ESTIMATION DÉTAILLÉE (interne)
A2: Bibliothèque Georgette-Lepage (Brossard) — Technologie RFID — aménagement RDC et étage
A3: Appel d'offres SP-GTER-26-0080 — Plans HF Experts-Conseils 26-29, émis pour AO 2026-09-16
A4: Cellules JAUNES = à remplir par Jo (prix matériel). Heures = estimé Léna AI à valider. Taux MO lié au Sommaire.
A6: Code | B6: Description | C6: Réf. plan | D6: Qté | E6: Unité | F6: Prix mat. unit. | G6: Total mat. | H6: h / unité | I6: Total h | J6: Total MO | K6: Total ligne | L6: Notes / source quantité
A7: A | B7: DÉMANTÈLEMENT / RELOCALISATION / TRAVAUX TEMPORAIRES
A8: A-01 | B8: Démantèlement luminaires existants RDC (E.A.E) — retirer alimentation jusqu'à la boîte/panneau | C8: E-201 | D8: 39 | E8: u | G8: =D8*F8 -> 0 | H8: 0.35 | I8: =D8*H8 -> 13.65 | J8: =I8*Sommaire!$C$6 -> 1692.6 | K8: =G8+J8 -> 1692.6 | L8: Compte des étiquettes E.A.E sur E-201
A9: A-02 | B9: Démantèlement luminaires existants 2e (E.A.E) | C9: E-202 | D9: 7 | E9: u | G9: =D9*F9 -> 0 | H9: 0.35 | I9: =D9*H9 -> 2.45 | J9: =I9*Sommaire!$C$6 -> 303.8 | K9: =G9+J9 -> 303.8 | L9: Compte E.A.E E-202
A10: A-03 | B10: Démantèlement services RDC (prises, boîtes mobilier, câbles sortant du plancher) E.A.E | C10: E-101 | D10: 34 | E10: u | G10: =D10*F10 -> 0 | H10: 0.4 | I10: =D10*H10 -> 13.6 | J10: =I10*Sommaire!$C$6 -> 1686.4 | K10: =G10+J10 -> 1686.4 | L10: Compte E.A.E E-101
A11: A-04 | B11: Démantèlement services 2e (E.A.E) | C11: E-102 | D11: 10 | E11: u | G11: =D11*F11 -> 0 | H11: 0.4 | I11: =D11*H11 -> 4 | J11: =I11*Sommaire!$C$6 -> 496 | K11: =G11+J11 -> 496 | L11: Compte E.A.E E-102
A12: A-05 | B12: Relocalisation équipements services (E.A.R) RDC + 2e | C12: E-101/E-102 | D12: 13 | E12: u | G12: =D12*F12 -> 0 | H12: 1 | I12: =D12*H12 -> 13 | J12: =I12*Sommaire!$C$6 -> 1612 | K12: =G12+J12 -> 1612 | L12: 6 RDC + 7 2e
A13: A-06 | B13: Relocalisation luminaires (E.A.R) RDC + 2e (incl. 4 appareils salle 227) | C13: E-201/E-202 | D13: 7 | E13: u | G13: =D13*F13 -> 0 | H13: 1 | I13: =D13*H13 -> 7 | J13: =I13*Sommaire!$C$6 -> 868 | K13: =G13+J13 -> 868 | L13: 3 RDC + 4 2e
A14: A-07 | B14: Relocalisation interrupteurs maîtres du hall (note spécifique 1 E-201) | C14: E-201 | D14: 1 | E14: lot | G14: =D14*F14 -> 0 | H14: 6 | I14: =D14*H14 -> 6 | J14: =I14*Sommaire!$C$6 -> 744 | K14: =G14+J14 -> 744 | L14: Hypothèse 6 h — à valider
A15: A-08 | B15: FabLab 210 : retrait temporaire + réinstallation luminaires linéaires existants | C15: E-202 note 1 | D15: 21 | E15: u | G15: =D15*F15 -> 0 | H15: 0.6 | I15: =D15*H15 -> 12.6 | J15: =I15*Sommaire!$C$6 -> 1562.4 | K15: =G15+J15 -> 1562.4 | L15: Comptés sur plan
A16: A-09 | B16: FabLab 210 : retrait temporaire + réinstallation encastrés existants | C16: E-202 note 1 | D16: 24 | E16: u | G16: =D16*F16 -> 0 | H16: 0.5 | I16: =D16*H16 -> 12 | J16: =I16*Sommaire!$C$6 -> 1488 | K16: =G16+J16 -> 1488 | L16: Comptés sur plan (±2)
A17: A-10 | B17: Toit : débrancher, entreposer sectionneurs, isoler/couvrir câbles, rebrancher équipements de ventilation (E.A.R) | C17: E-103/E-106 note 2 | D17: 6 | E17: u | G17: =D17*F17 -> 0 | H17: 4 | I17: =D17*H17 -> 24 | J17: =I17*Sommaire!$C$6 -> 2976 | K17: =G17+J17 -> 2976 | L17: 6 E.A.R sur E-103
A18: A-11 | B18: Maintien continuité de service, recherche/traçage circuits existants, réalimentation circuits libérés | C18: Notes 1.16 / 5-6 | D18: 1 | E18: lot | G18: =D18*F18 -> 0 | H18: 16 | I18: =D18*H18 -> 16 | J18: =I18*Sommaire!$C$6 -> 1984 | K18: =G18+J18 -> 1984 | L18: Hypothèse
B19: Sous-total section A | G19: =SUM(G8:G18) -> 0 | I19: =SUM(I8:I18) -> 124.3 | J19: =SUM(J8:J18) -> 15413.2 | K19: =SUM(K8:K18) -> 15413.2
A21: B | B21: DISTRIBUTION / PANNEAUX
A22: B-01 | B22: Panneau PP-3 NEUF 225A 347/600V 3Ø 4F 42 cct 14kA, type NF Schneider, surface — remplacement de l'existant (note 2 E-006) | C22: E-006/E-502 | D22: 1 | E22: u | G22: =D22*F22 -> 0 | H22: 24 | I22: =D22*H22 -> 24 | J22: =I22*Sommaire!$C$6 -> 2976 | K22: =G22+J22 -> 2976 | L22: Incl. démantèlement ancien PP-3 + transfert charges
A23: B-02 | B23: Disjoncteurs NF 1P-15A pour circuits existants transférés dans PP-3 | C23: E-502 | D23: 14 | E23: u | G23: =D23*F23 -> 0 | H23: 0.5 | I23: =D23*H23 -> 7 | J23: =I23*Sommaire!$C$6 -> 868 | K23: =G23+J23 -> 868 | L23: Cct 1-11, 2-12, 14 (PR-2), 16
A24: B-03 | B24: Disjoncteur NF 3P-20A (aérotherme, cct 13-15-17) transféré | C24: E-502 | D24: 1 | E24: u | G24: =D24*F24 -> 0 | H24: 0.75 | I24: =D24*H24 -> 0.75 | J24: =I24*Sommaire!$C$6 -> 93 | K24: =G24+J24 -> 93
A25: B-04 | B25: Disjoncteur NF 3P-40A — UTA-1 (cct 18-20-22) NOUVEAU | C25: E-502 | D25: 1 | E25: u | G25: =D25*F25 -> 0 | H25: 0.75 | I25: =D25*H25 -> 0.75 | J25: =I25*Sommaire!$C$6 -> 93 | K25: =G25+J25 -> 93 | L25: Note : tableau méca indique MOCP 35A — à clarifier ingénieur
A26: B-05 | B26: Disjoncteur NF 3P-15A — VE-2N (cct 19-21-23) NOUVEAU | C26: E-502 | D26: 1 | E26: u | G26: =D26*F26 -> 0 | H26: 0.75 | I26: =D26*H26 -> 0.75 | J26: =I26*Sommaire!$C$6 -> 93 | K26: =G26+J26 -> 93
A27: B-06 | B27: Disjoncteur 1P-15A DDFT — Fontaine P2-61 (note 4) | C27: E-502 | D27: 1 | E27: u | G27: =D27*F27 -> 0 | H27: 0.75 | I27: =D27*H27 -> 0.75 | J27: =I27*Sommaire!$C$6 -> 93 | K27: =G27+J27 -> 93
A28: B-07 | B28: Disjoncteurs 1P-15A — P2-63 bornes prêts hall, P2-64 prises bibliothèque (note 4) | C28: E-502 | D28: 2 | E28: u | G28: =D28*F28 -> 0 | H28: 0.5 | I28: =D28*H28 -> 1 | J28: =I28*Sommaire!$C$6 -> 124 | K28: =G28+J28 -> 124
A29: B-08 | B29: Disjoncteurs 1P-20A — P3-17/19 machine de tri (note 4) | C29: E-502 | D29: 2 | E29: u | G29: =D29*F29 -> 0 | H29: 0.5 | I29: =D29*H29 -> 1 | J29: =I29*Sommaire!$C$6 -> 124 | K29: =G29+J29 -> 124
A30: B-09 | B30: Mise à jour fiches dactylographiées + identification (PP-2, PP-3, P2, P3, P4, P6, PU-1, PPU-1, P10) | C30: Devis 12.3 | D30: 9 | E30: u | G30: =D30*F30 -> 0 | H30: 1 | I30: =D30*H30 -> 9 | J30: =I30*Sommaire!$C$6 -> 1116 | K30: =G30+J30 -> 1116
B31: Sous-total section B | G31: =SUM(G22:G30) -> 0 | I31: =SUM(I22:I30) -> 45 | J31: =SUM(J22:J30) -> 5580 | K31: =SUM(K22:K30) -> 5580
A33: C | B33: RACCORDEMENTS MÉCANIQUES
A34: C-01 | B34: UTA-01 York KE036 575V/3Ø (MCA 32.9A) au toit — conduit EMT 1" + RW90 4 #8 (3+MALT) de PP-3 (salle méc. étage), pénétration toit, raccord LFMC — sectionneur d'usine | C34: E-106/E-009 | D34: 1 | E34: u | G34: =D34*F34 -> 0 | H34: 16 | I34: =D34*H34 -> 16 | J34: =I34*Sommaire!$C$6 -> 1984 | K34: =G34+J34 -> 1984 | L34: Longueur estimée 35 m (C-05/C-06)
A35: C-02 | B35: VE-02N Plymovent FUA-2700 1.5HP 575V/3Ø c/a VFD au toit — conduit EMT 3/4" + RW90 4 #12, raccord LFMC — sectionneur d'usine | C35: E-106/E-009 | D35: 1 | E35: u | G35: =D35*F35 -> 0 | H35: 10 | I35: =D35*H35 -> 10 | J35: =I35*Sommaire!$C$6 -> 1240 | K35: =G35+J35 -> 1240 | L35: Longueur estimée 35 m
A36: C-03 | B36: Chaudières CH-01 / CH-02 De Dietrich 600V/3Ø — vérifier et réutiliser tiroirs CCM-1 F15A + câbles existants, raccord final LFMC | C36: E-006 note 1 / E-105 | D36: 2 | E36: u | G36: =D36*F36 -> 0 | H36: 6 | I36: =D36*H36 -> 12 | J36: =I36*Sommaire!$C$6 -> 1488 | K36: =G36+J36 -> 1488 | L36: Réutilisation selon état — à vérifier
A37: C-04 | B37: Humidificateurs HUM-1/2/3 Carel 120V/1Ø — sectionneur sans fusible 30A 1Ø + conduit EMT 3/4" 3 #12 (P4-19, P4-21) + raccord LFMC | C37: E-105/E-009 | D37: 3 | E37: u | G37: =D37*F37 -> 0 | H37: 4 | I37: =D37*H37 -> 12 | J37: =I37*Sommaire!$C$6 -> 1488 | K37: =G37+J37 -> 1488 | L37: 15 m chacun estimé
A38: C-05 | B38: Conduit EMT 1" (alim. UTA-01) incl. supports | C38: E-106 | D38: 35 | E38: m | G38: =D38*F38 -> 0 | H38: 0.12 | I38: =D38*H38 -> 4.2 | J38: =I38*Sommaire!$C$6 -> 520.8 | K38: =G38+J38 -> 520.8 | L38: Hypothèse longueur
A39: C-06 | B39: Conducteur RW90 #8 Cu (UTA-01) | C39: E-106 | D39: 140 | E39: m | G39: =D39*F39 -> 0 | H39: 0.015 | I39: =D39*H39 -> 2.1 | J39: =I39*Sommaire!$C$6 -> 260.4 | K39: =G39+J39 -> 260.4 | L39: 4 x 35 m
A40: C-07 | B40: Conduit EMT 3/4" (VE-02N + HUM) | C40: E-105/E-106 | D40: 80 | E40: m | G40: =D40*F40 -> 0 | H40: 0.09 | I40: =D40*H40 -> 7.2 | J40: =I40*Sommaire!$C$6 -> 892.8 | K40: =G40+J40 -> 892.8 | L40: 35 m + 3 x 15 m
A41: C-08 | B41: Conducteur RW90 #12 Cu (VE-02N + HUM) | C41: E-105/E-106 | D41: 275 | E41: m | G41: =D41*F41 -> 0 | H41: 0.012 | I41: =D41*H41 -> 3.3 | J41: =I41*Sommaire!$C$6 -> 409.2 | K41: =G41+J41 -> 409.2 | L41: 4x35 + 3x(3x15)
B42: Sous-total section C | G42: =SUM(G34:G41) -> 0 | I42: =SUM(I34:I41) -> 66.8 | J42: =SUM(J34:J41) -> 8283.2 | K42: =SUM(K34:K41) -> 8283.2
A44: D | B44: SERVICES — REZ-DE-CHAUSSÉE (E-104)
A45: D-01 | B45: Poste de travail intégré mobilier (notes 1-2) : boîte de jonction, 1 prise double 15A + 1 prise double 20A Decora, boîte data 2 RJ45 (plaque seulement), raccord câbles réutilisés | C45: E-104 | D45: 18 | E45: poste | G45: =D45*F45 -> 0 | H45: 1.5 | I45: =D45*H45 -> 27 | J45: =I45*Sommaire!$C$6 -> 3348 | K45: =G45+J45 -> 3348 | L45: 110.13/14:3, Doc 110.1:4, 110.7:2, 110.8:4, 116:2, aire centrale:3
A46: D-02 | B46: Table c/a boîte d'électrification (note 4) : 2 prises doubles + 2 prises USB Leviton Decora | C46: E-104 | D46: 5 | E46: u | G46: =D46*F46 -> 0 | H46: 1.5 | I46: =D46*H46 -> 7.5 | J46: =I46*Sommaire!$C$6 -> 930 | K46: =G46+J46 -> 930 | L46: 115:3, aire centrale:2
A47: D-03 | B47: Cabine/isoloir : prise double alimentée par JB dans mur | C47: E-104 | D47: 2 | E47: u | G47: =D47*F47 -> 0 | H47: 1 | I47: =D47*H47 -> 2 | J47: =I47*Sommaire!$C$6 -> 248 | K47: =G47+J47 -> 248 | L47: P-2 20
A48: D-04 | B48: Écran sur mur/colonne — boîte courant + données | C48: E-104 | D48: 2 | E48: u | G48: =D48*F48 -> 0 | H48: 1 | I48: =D48*H48 -> 2 | J48: =I48*Sommaire!$C$6 -> 248 | K48: =G48+J48 -> 248 | L48: 115 + colonne aire centrale
A49: D-05 | B49: Kiosque TV (P-2 6) — prise + data | C49: E-104 | D49: 1 | E49: u | G49: =D49*F49 -> 0 | H49: 1 | I49: =D49*H49 -> 1 | J49: =I49*Sommaire!$C$6 -> 124 | K49: =G49+J49 -> 124
A50: D-06 | B50: Prise double murale/colonne NEUVE (P-3 2, 3, 10, 12, 34 x2, 35 + P-2 11) | C50: E-104 | D50: 8 | E50: u | G50: =D50*F50 -> 0 | H50: 0.75 | I50: =D50*H50 -> 6 | J50: =I50*Sommaire!$C$6 -> 744 | K50: =G50+J50 -> 744
A51: D-07 | B51: Prise DDFT 15A fontaine (P2-61) | C51: E-104 | D51: 1 | E51: u | G51: =D51*F51 -> 0 | H51: 1 | I51: =D51*H51 -> 1 | J51: =I51*Sommaire!$C$6 -> 124 | K51: =G51+J51 -> 124
A52: D-08 | B52: Sortie data murale/colonne : boîte + conduit 3/4" vers entreplafond + corde de tirage | C52: E-104 | D52: 10 | E52: u | G52: =D52*F52 -> 0 | H52: 0.75 | I52: =D52*H52 -> 7.5 | J52: =I52*Sommaire!$C$6 -> 930 | K52: =G52+J52 -> 930 | L52: Câble data : voir option
A53: D-09 | B53: Barrière anti-vol : 2 boîtes de jonction + raccord panneau de contrôle (PU-1 23) | C53: E-104 | D53: 1 | E53: lot | G53: =D53*F53 -> 0 | H53: 6 | I53: =D53*H53 -> 6 | J53: =I53*Sommaire!$C$6 -> 744 | K53: =G53+J53 -> 744
A54: D-10 | B54: Bornes de prêts / fontaine hall (P2-63, note 2) — JB dans mur adjacent | C54: E-104 | D54: 1 | E54: u | G54: =D54*F54 -> 0 | H54: 2 | I54: =D54*H54 -> 2 | J54: =I54*Sommaire!$C$6 -> 248 | K54: =G54+J54 -> 248
A55: D-11 | B55: Bouton d'appel — boîte + conduit vide (système fourni par d'autres) | C55: E-104 | D55: 1 | E55: u | G55: =D55*F55 -> 0 | H55: 1 | I55: =D55*H55 -> 1 | J55: =I55*Sommaire!$C$6 -> 124 | K55: =G55+J55 -> 124 | L55: Aide au lecteur 116
A56: D-12 | B56: Percement de dalle carotté + coupe-feu (CAN/ULC-S115, Hilti CP-506) — conduits sous dalle (note 5) | C56: E-104 note 5 / devis 1.5, 18 | D56: 16 | E56: u | G56: =D56*F56 -> 0 | H56: 1.5 | I56: =D56*H56 -> 24 | J56: =I56*Sommaire!$C$6 -> 2976 | K56: =G56+J56 -> 2976 | L56: 1 percement par course
A57: D-13 | B57: Conduit EMT 1" sous dalle / entreplafond sous-sol vers panneaux P-2/P-3 (16 courses) | C57: E-104 note 5 | D57: 480 | E57: m | G57: =D57*F57 -> 0 | H57: 0.12 | I57: =D57*H57 -> 57.6 | J57: =I57*Sommaire!$C$6 -> 7142.4 | K57: =G57+J57 -> 7142.4 | L57: Hyp. 30 m/course
A58: D-14 | B58: Conduit EMT 3/4" data sous dalle (11 courses) | C58: E-104 note 5 | D58: 330 | E58: m | G58: =D58*F58 -> 0 | H58: 0.09 | I58: =D58*H58 -> 29.7 | J58: =I58*Sommaire!$C$6 -> 3682.8 | K58: =G58+J58 -> 3682.8 | L58: Hyp. 30 m/course
A59: D-15 | B59: Conducteur RW90 #12 Cu (5 cond./course : 2 circuits + MALT) — prévoir #10 si chute > 3 % | C59: E-104 note 6 | D59: 2400 | E59: m | G59: =D59*F59 -> 0 | H59: 0.012 | I59: =D59*H59 -> 28.8 | J59: =I59*Sommaire!$C$6 -> 3571.2 | K59: =G59+J59 -> 3571.2 | L59: 16 x 30 m x 5
A60: D-16 | B60: Boîtes de tirage/jonction, connecteurs, supports, corde de tirage — conduits sous dalle | C60: E-104 | D60: 1 | E60: lot | G60: =D60*F60 -> 0 | H60: 8 | I60: =D60*H60 -> 8 | J60: =I60*Sommaire!$C$6 -> 992 | K60: =G60+J60 -> 992
B61: Sous-total section D | G61: =SUM(G45:G60) -> 0 | I61: =SUM(I45:I60) -> 211.1 | J61: =SUM(J45:J60) -> 26176.4 | K61: =SUM(K45:K60) -> 26176.4
A63: E | B63: SERVICES — ÉTAGE (E-105)
A64: E-01 | B64: Poste de travail aide au lecteur 227 (P-6 5 / P-4 7) : JB, 2 prises, data 2 RJ45 | C64: E-105 | D64: 2 | E64: poste | G64: =D64*F64 -> 0 | H64: 1.5 | I64: =D64*H64 -> 3 | J64: =I64*Sommaire!$C$6 -> 372 | K64: =G64+J64 -> 372
A65: E-02 | B65: Monument de plancher Hubbell S1R6PTFIT (ou équiv.) : prise 20A + 2 RJ45 — tables | C65: E-104 note 3 / E-105 | D65: 2 | E65: u | G65: =D65*F65 -> 0 | H65: 2.5 | I65: =D65*H65 -> 5 | J65: =I65*Sommaire!$C$6 -> 620 | K65: =G65+J65 -> 620 | L65: P-4 17, P4-15
A66: E-03 | B66: Boîte de plancher refaite (salle 208, ancien mobilier — note 1 E-102) | C66: E-102/E-105 | D66: 2 | E66: u | G66: =D66*F66 -> 0 | H66: 2.5 | I66: =D66*H66 -> 5 | J66: =I66*Sommaire!$C$6 -> 620 | K66: =G66+J66 -> 620 | L66: P-6 25 / P-6 38 — à confirmer
A67: E-04 | B67: Cabines/salles (P-4 12, 10, 10) : JB + prise | C67: E-105 | D67: 3 | E67: u | G67: =D67*F67 -> 0 | H67: 1 | I67: =D67*H67 -> 3 | J67: =I67*Sommaire!$C$6 -> 372 | K67: =G67+J67 -> 372
A68: E-05 | B68: Écran sur colonne — courant + données (P-6 12) | C68: E-105 | D68: 1 | E68: u | G68: =D68*F68 -> 0 | H68: 1 | I68: =D68*H68 -> 1 | J68: =I68*Sommaire!$C$6 -> 124 | K68: =G68+J68 -> 124
A69: E-06 | B69: Bouton d'appel (2) + bouton de panique (1) — boîte + conduit vide | C69: E-105 | D69: 3 | E69: u | G69: =D69*F69 -> 0 | H69: 1 | I69: =D69*H69 -> 3 | J69: =I69*Sommaire!$C$6 -> 372 | K69: =G69+J69 -> 372
A70: E-07 | B70: Percement de dalle carotté + coupe-feu (7 courses) | C70: E-105 note 3 | D70: 7 | E70: u | G70: =D70*F70 -> 0 | H70: 1.5 | I70: =D70*H70 -> 10.5 | J70: =I70*Sommaire!$C$6 -> 1302 | K70: =G70+J70 -> 1302
A71: E-08 | B71: Conduit EMT 1" sous dalle (7 courses) vers P-4/P-6 | C71: E-105 note 3 | D71: 175 | E71: m | G71: =D71*F71 -> 0 | H71: 0.12 | I71: =D71*H71 -> 21 | J71: =I71*Sommaire!$C$6 -> 2604 | K71: =G71+J71 -> 2604 | L71: Hyp. 25 m/course
A72: E-09 | B72: Conduit EMT 3/4" data sous dalle (7 courses) | C72: E-105 note 3 | D72: 175 | E72: m | G72: =D72*F72 -> 0 | H72: 0.09 | I72: =D72*H72 -> 15.75 | J72: =I72*Sommaire!$C$6 -> 1953 | K72: =G72+J72 -> 1953 | L72: Hyp. 25 m/course
A73: E-10 | B73: Conducteur RW90 #12 Cu (5 cond./course) | C73: E-105 | D73: 875 | E73: m | G73: =D73*F73 -> 0 | H73: 0.012 | I73: =D73*H73 -> 10.5 | J73: =I73*Sommaire!$C$6 -> 1302 | K73: =G73+J73 -> 1302 | L73: 7 x 25 m x 5
A74: E-11 | B74: Boîtes, connecteurs, supports — étage | C74: E-105 | D74: 1 | E74: lot | G74: =D74*F74 -> 0 | H74: 4 | I74: =D74*H74 -> 4 | J74: =I74*Sommaire!$C$6 -> 496 | K74: =G74+J74 -> 496
B75: Sous-total section E | G75: =SUM(G64:G74) -> 0 | I75: =SUM(I64:I74) -> 81.75 | J75: =SUM(J64:J74) -> 10137 | K75: =SUM(K64:K74) -> 10137
A77: F | B77: ÉCLAIRAGE ET ÉCLAIRAGE D'URGENCE — RDC (E-203)
A78: F-01 | B78: Luminaire A1 — Cooper 24CGTS-NUV-MEDIUM-3500K, 2'x4' encastré, 347V, 50W | C78: E-203/E-008 | D78: 11 | E78: u | G78: =D78*F78 -> 0 | H78: 1 | I78: =D78*H78 -> 11 | J78: =I78*Sommaire!$C$6 -> 1364 | K78: =G78+J78 -> 1364 | L78: Dont 3 sur circuit PP-U1
A79: F-02 | B79: Luminaire C1 — Axis AXIS-SL1-4-SO-500-90HE-35 (module 4'), 120-277V, susp./surface | C79: E-203/E-008 | D79: 12 | E79: u | G79: =D79*F79 -> 0 | H79: 0.75 | I79: =D79*H79 -> 9 | J79: =I79*Sommaire!$C$6 -> 1116 | K79: =G79+J79 -> 1116
A80: F-03 | B80: Luminaire C1_1 — Axis AXIS-SL1-1 (module 1') | C80: E-203/E-008 | D80: 6 | E80: u | G80: =D80*F80 -> 0 | H80: 0.5 | I80: =D80*H80 -> 3 | J80: =I80*Sommaire!$C$6 -> 372 | K80: =G80+J80 -> 372
A81: F-04 | B81: Luminaire C1_3 — Axis AXIS-SL1-3 (module 3') | C81: E-203/E-008 | D81: 15 | E81: u | G81: =D81*F81 -> 0 | H81: 0.6 | I81: =D81*H81 -> 9 | J81: =I81*Sommaire!$C$6 -> 1116 | K81: =G81+J81 -> 1116
A82: F-05 | B82: Rangées linéaires Axis : suspension aux tiges/câbles fixés à la dalle (devis 16.5), alimentation de rangée | C82: E-203 / devis 16.5 | D82: 20 | E82: rangée | G82: =D82*F82 -> 0 | H82: 1 | I82: =D82*H82 -> 20 | J82: =I82*Sommaire!$C$6 -> 2480 | K82: =G82+J82 -> 2480 | L82: ≈20 rangées continues
A83: F-06 | B83: Luminaire E — GreenCreative PXCYL-8-PM-LE05-90-35 cylindre suspendu, 55.3W | C83: E-203/E-008 | D83: 4 | E83: u | G83: =D83*F83 -> 0 | H83: 1.25 | I83: =D83*H83 -> 5 | J83: =I83*Sommaire!$C$6 -> 620 | K83: =G83+J83 -> 620
A84: F-07 | B84: Enseigne de sortie Z6 — Stanpro RMSOWH-UDC, 120-347V, 3W (pictogramme) | C84: E-203/E-008 | D84: 3 | E84: u | G84: =D84*F84 -> 0 | H84: 1.5 | I84: =D84*H84 -> 4.5 | J84: =I84*Sommaire!$C$6 -> 558 | K84: =G84+J84 -> 558 | L84: Symboles noirs (neufs)
A85: F-08 | B85: Conduit EMT 3/4" + flexible — raccordement luminaires sur circuits existants réutilisés (note 5) | C85: E-203 | D85: 280 | E85: m | G85: =D85*F85 -> 0 | H85: 0.08 | I85: =D85*H85 -> 22.4 | J85: =I85*Sommaire!$C$6 -> 2777.6 | K85: =G85+J85 -> 2777.6 | L85: Hyp. 8 m x 35 points
A86: F-09 | B86: Conducteur RW90 #12 Cu éclairage (3 cond.) | C86: E-203 | D86: 840 | E86: m | G86: =D86*F86 -> 0 | H86: 0.012 | I86: =D86*H86 -> 10.08 | J86: =I86*Sommaire!$C$6 -> 1249.92 | K86: =G86+J86 -> 1249.92
A87: F-10 | B87: Boîtes de jonction éclairage, chaînes de retenue à la dalle (devis 16.5), quincaillerie | C87: E-005 | D87: 1 | E87: lot | G87: =D87*F87 -> 0 | H87: 8 | I87: =D87*H87 -> 8 | J87: =I87*Sommaire!$C$6 -> 992 | K87: =G87+J87 -> 992
B88: Sous-total section F | G88: =SUM(G78:G87) -> 0 | I88: =SUM(I78:I87) -> 101.98 | J88: =SUM(J78:J87) -> 12645.52 | K88: =SUM(K78:K87) -> 12645.52
A90: G | B90: ALARME INCENDIE (travaux par l'électricien — note 4 E-201)
A91: G-01 | B91: Détecteur de fumée adressable compatible Simplex 4007ES + base (fourni par JCI/Simplex) | C91: E-203 | D91: 2 | E91: u | G91: =D91*F91 -> 0 | H91: 1.5 | I91: =D91*H91 -> 3 | J91: =I91*Sommaire!$C$6 -> 372 | K91: =G91+J91 -> 372 | L91: Symboles noirs : salle de tri + secteur 110.8
A92: G-02 | B92: Conduit EMT 3/4" boucle AI | C92: E-203 | D92: 30 | E92: m | G92: =D92*F92 -> 0 | H92: 0.09 | I92: =D92*H92 -> 2.7 | J92: =I92*Sommaire!$C$6 -> 334.8 | K92: =G92+J92 -> 334.8 | L92: Hyp.
A93: G-03 | B93: Câble AI FT4 2c #16 rouge (boucle adressable) | C93: E-203 | D93: 60 | E93: m | G93: =D93*F93 -> 0 | H93: 0.015 | I93: =D93*H93 -> 0.9 | J93: =I93*Sommaire!$C$6 -> 111.6 | K93: =G93+J93 -> 111.6 | L93: Hyp.
A94: G-04 | B94: Relocalisation panneau annonciateur Simplex — réutiliser câbles, rallonger au besoin (note 1 E-007) | C94: E-007 | D94: 1 | E94: u | G94: =D94*F94 -> 0 | H94: 6 | I94: =D94*H94 -> 6 | J94: =I94*Sommaire!$C$6 -> 744 | K94: =G94+J94 -> 744 | L94: Nouvel emplacement à confirmer
A95: G-05 | B95: Démontage/protection/réinstallation dispositifs AI existants dans zones touchées | C95: E-201/E-203 | D95: 1 | E95: lot | G95: =D95*F95 -> 0 | H95: 12 | I95: =D95*H95 -> 12 | J95: =I95*Sommaire!$C$6 -> 1488 | K95: =G95+J95 -> 1488 | L95: Allocation — à valider
A96: G-06 | B96: Assistance électricien lors de la programmation / vérification ULC-S537 | C96: E-007 note 3 | D96: 1 | E96: lot | G96: =D96*F96 -> 0 | H96: 8 | I96: =D96*H96 -> 8 | J96: =I96*Sommaire!$C$6 -> 992 | K96: =G96+J96 -> 992
A97: G-07 | B97: Sous-traitance JCI/Simplex : bypass durée des travaux, programmation 4007ES, vérification partielle CAN/ULC-S537, certificat de conformité | C97: E-007 notes 2-3 | D97: 1 | E97: lot | G97: =D97*F97 -> 0 | H97: 0 | I97: =D97*H97 -> 0 | J97: =I97*Sommaire!$C$6 -> 0 | K97: =G97+J97 -> 0 | L97: PRIX À OBTENIR DE JCI — inscrire en matériel/s-t
B98: Sous-total section G | G98: =SUM(G91:G97) -> 0 | I98: =SUM(I91:I97) -> 32.6 | J98: =SUM(J91:J97) -> 4042.4 | K98: =SUM(K91:K97) -> 4042.4
A100: H | B100: FRAIS DE CHANTIER / GÉNÉRAUX
A101: H-01 | B101: Mobilisation / démobilisation, outillage, plateforme/échafaudage roulant | D101: 1 | E101: lot | G101: =D101*F101 -> 0 | H101: 16 | I101: =D101*H101 -> 16 | J101: =I101*Sommaire!$C$6 -> 1984 | K101: =G101+J101 -> 1984 | L101: Hypothèse
A102: H-02 | B102: Coordination EG / multi-corps, dessins d'atelier, plans tel que construit | C102: Devis 1.11-1.13 | D102: 1 | E102: lot | G102: =D102*F102 -> 0 | H102: 20 | I102: =D102*H102 -> 20 | J102: =I102*Sommaire!$C$6 -> 2480 | K102: =G102+J102 -> 2480 | L102: Hypothèse
A103: H-03 | B103: Essais, mise en service, vérification prises existantes (note 3), étiquetage | C103: Devis 1.11 / note 3 | D103: 1 | E103: lot | G103: =D103*F103 -> 0 | H103: 12 | I103: =D103*H103 -> 12 | J103: =I103*Sommaire!$C$6 -> 1488 | K103: =G103+J103 -> 1488 | L103: Hypothèse
A104: H-04 | B104: Nettoyage, gestion des déchets (devis 5, 9.3) | D104: 1 | E104: lot | G104: =D104*F104 -> 0 | H104: 8 | I104: =D104*H104 -> 8 | J104: =I104*Sommaire!$C$6 -> 992 | K104: =G104+J104 -> 992 | L104: Hypothèse
B105: Sous-total section H | G105: =SUM(G101:G104) -> 0 | I105: =SUM(I101:I104) -> 56 | J105: =SUM(J101:J104) -> 6944 | K105: =SUM(K101:K104) -> 6944
A107: OPT | B107: OPTIONS / À CLARIFIER (hors total)
A108: OPT-1 | B108: Câblage data Cat6 jusqu'à la salle des serveurs (devis 36.1) — vs plans « réutiliser câble data existant » : CONTRADICTION à clarifier | C108: Devis 36.1 / E-104 note 2 | L108: Nb de sorties RJ45 ≈ 2 x postes + sorties murales
A109: OPT-2 | B109: Conception parasismique par firme spécialisée + certificat (devis 16.2-16.6) | C109: Devis 16 | D109: 1 | E109: lot | L109: Prix sous-traitant à obtenir
...

Sheet Matériel Lumen
A1: LISTE DE MATÉRIEL — CONDUITS / FILAGE / BOÎTES / DISPOSITIFS
A2: Prix Lumen — compte LE GROUPE DR ÉLECTRIQUE INC (4417250), succ. Anjou, relevés sur lumen.ca le 2026-10-07 (prix réguliers du compte, aucun prix promo)
A3: EXCLUS de cette liste (demandes de prix séparées) : luminaires + urgence, dispositifs AI Simplex, panneau PP-3 + disjoncteurs NF Schneider (non offerts en ligne chez Lumen), disjoncteurs P2/P3 (marque à confirmer).
A5: Code Lumen | B5: Description | C5: Qté | D5: Unité | E5: Prix unit. | F5: Total | G5: Base de quantité
A6: CONDUITS ET ACCESSOIRES
A7: CONEMT1 | B7: COLUMBIA 1 PO CONDUIT TME 10PI 734637 | C7: 2270 | D7: pi | E7: 1.8378 | F7: =C7*E7 -> 4171.806 | G7: 690 m (C-05 35 + D-13 480 + E-08 175)
A8: CONEMT3/4 | B8: COLUMBIA 3/4 PO CONDUIT TME 10PI 734631 | C8: 2940 | D8: pi | E8: 1.0494 | F8: =C8*E8 -> 3085.236 | G8: 895 m (C-07 80 + D-14 330 + E-09 175 + F-08 280 + G-02 30)
A9: APPTWC100S | B9: ABB CI5508 ACCOUPL TME 1PO VIS ACIER | C9: 227 | D9: ch | E9: 1.3118 | F9: =C9*E9 -> 297.7786 | G9: 1 / 10 pi
A10: APPTWC75S | B10: ABB CI5506 ACCOUPL TME 3/4PO VIS ACIER | C10: 294 | D10: ch | E10: 0.8047 | F10: =C10*E10 -> 236.5818 | G10: 1 / 10 pi
A11: APPTW100S | B11: ABB Iberville 1 PO CONN TME VIS ACIER CI5408 | C11: 96 | D11: ch | E11: 1.4344 | F11: =C11*E11 -> 137.7024 | G11: 24 courses x 4
A12: APPTW75S | B12: ABB Iberville 3/4 PO CONN TME VIS ACIER CI5406 | C12: 280 | D12: ch | E12: 0.9097 | F12: =C12*E12 -> 254.716 | G12: ≈70 courses x 4
A13: APPTWCL100 | B13: ABB Iberville 1 PO COURR TME 1 TROU ACIER | C13: 460 | D13: ch | E13: 0.5813 | F13: =C13*E13 -> 267.398 | G13: 1 / 1,5 m (devis 15.1)
A14: APPTWCL75 | B14: ABB Iberville 3/4 PO COURR TME 1 TROU ACIER CI1306 | C14: 600 | D14: ch | E14: 0.2732 | F14: =C14*E14 -> 163.92 | G14: 1 / 1,5 m
A15: CONCONSEAL3/4 | B15: COLUMBIA Hydrotite 3/4 PO COND FLEX ÉTANCHE | C15: 14 | D15: m | E15: 12.4001 | F15: =C15*E15 -> 173.6014 | G15: UTA, VE-02N, HUM x3, CH x2
A16: THO5333 | B16: ABB 3/4 PO CONN CONSEAL ISOLÉ 5333 | C16: 20 | D16: ch | E16: 15.1394 | F16: =C16*E16 -> 302.788
A17: THOABRH03830 | B17: ABB 3/8 PO COND FLEX ALUM ABRH038-30 | C17: 63 | D17: m | E17: 7.714 | F17: =C17*E17 -> 485.982 | G17: 35 points éclairage x 1,8 m
A18: IBE2210 | B18: ABB Iberville 3/8 PO CONN BX 90D 2 VIS | C18: 70 | D18: ch | E18: 1.799 | F18: =C18*E18 -> 125.93
A19: GRE430 | B19: Corde de tirage Poly Line 430 - 6500 pi | C19: 1 | D19: ch | E19: 81.68 | F19: =C19*E19 -> 81.68 | G19: Conduits vides (devis 35.10)
A20: BOÎTES
A21: IBE52151K | B21: ABB BC52151-K BOÎTE CARRÉE 4 PO 1-1/2PO | C21: 66 | D21: ch | E21: 5.2196 | F21: =C21*E21 -> 344.4936 | G21: Prises, data, JB postes, boutons, barrières
A22: IBE52C13 | B22: IBERVILLE Couvercle carré 1 unité 1/2 PO surélevé | C22: 66 | D22: ch | E22: 4.0873 | F22: =C22*E22 -> 269.7618
A23: IBE72171K | B23: IBERVILLE Boîte carrée 4-11/16 PO | C23: 46 | D23: ch | E23: 6.0543 | F23: =C23*E23 -> 278.4978 | G23: Tirage : 23 courses sous dalle x 2
A24: IBE72C1 | B24: ABB BC72-C-1 COUV CARRÉ 4-11/16 PO PLAT | C24: 46 | D24: ch | E24: 3.2082 | F24: =C24*E24 -> 147.5772
A25: IBE54151L | B25: IBERVILLE Boîte octogonale 4 PO 1-1/2 PO | C25: 35 | D25: ch | E25: 2.5048 | F25: =C25*E25 -> 87.668 | G25: JB éclairage
A26: FILS ET CÂBLES
A27: CAB12/1RW90BLK300 | B27: RW90 #12 solide Cu NOIR (bobine 300 m) | C27: 1500 | D27: m | E27: 1.3357 | F27: =C27*E27 -> 2003.55 | G27: Total #12 = 4 390 m (C-08 275 + D-15 2400 + E-10 875 + F-09 840)
A28: CAB12/1RW90WHI300 | B28: RW90 #12 solide Cu BLANC (bobine 300 m) | C28: 1200 | D28: m | E28: 1.3357 | F28: =C28*E28 -> 1602.84
A29: CAB12/1RW90GRE300 | B29: RW90 #12 solide Cu VERT (bobine 300 m) | C29: 900 | D29: m | E29: 1.3357 | F29: =C29*E29 -> 1202.13
A30: CAB12/1RW90 ROUGE | B30: RW90 #12 solide Cu ROUGE — même prix que noir (à confirmer code) | C30: 790 | D30: m | E30: 1.3357 | F30: =C30*E30 -> 1055.203 | G30: Code exact à confirmer
A31: CAB8RW90BLK | B31: SONECABLE 8(7) RW90 BLK (UTA-01) | C31: 105 | D31: m | E31: 4.5914 | F31: =C31*E31 -> 482.097 | G31: 3 phases x 35 m — prévoir rouge/bleu
A32: CAB8RW90GRE | B32: SONECABLE 8(7) RW90 GRE (MALT UTA-01) | C32: 35 | D32: m | E32: 4.5914 | F32: =C32*E32 -> 160.699
A33: CAB12TECK3C600V | B33: SONECABLE TECK90 3C #12 600V (chaudières) | C33: 10 | D33: m | E33: 9.1875 | F33: =C33*E33 -> 91.875
A34: IBETEK75120 | B34: ABB Star Teck 3/4 PO CONN TECK | C34: 4 | D34: ch | E34: 42.2247 | F34: =C34*E34 -> 168.8988 | G34: Plage à confirmer selon DE du câble
A35: CAB16/2FAFT4300 | B35: SONECABLE 16/2 FA FT4 (alarme incendie) | C35: 60 | D35: m | E35: 1.344 | F35: =C35*E35 -> 80.64 | G35: G-03
A36: DISPOSITIFS
A37: LEV16252W | B37: LEVITON 16252-W PRISE DÉCORA 15A 125V usage commercial | C37: 47 | D37: ch | E37: 8.32 | F37: =C37*E37 -> 391.04 | G37: Postes 20, tables 10, cabines 5, écrans 3, kiosque 1, murales 8
A38: LEV16352W | B38: LEVITON 16352-W PRISE DÉCORA 20A 125V usage commercial | C38: 20 | D38: ch | E38: 8.82 | F38: =C38*E38 -> 176.4 | G38: Postes
A39: LEVT5633W | B39: LEVITON T5633-W PRISE + CHARGEUR USB A/C | C39: 10 | D39: ch | E39: 48.66 | F39: =C39*E39 -> 486.6 | G39: Tables note 4 (2/table) — vérifier 5,1 A
A40: LEVGFNT1W | B40: LEVITON GFNT1-W PRISE DDFT 15A | C40: 1 | D40: ch | E40: 19.95 | F40: =C40*E40 -> 19.95 | G40: Fontaine
A41: LEV80401NW | B41: LEVITON 80401-NW PLAQUE DÉCORA 1G NYLON BLANC | C41: 66 | D41: ch | E41: 1.18 | F41: =C41*E41 -> 77.88
A42: HUBS1R6PTDEHBLK | B42: HUBBELL S1R6PTDEHBLK POKE-THROUGH 6 PO (plan : S1R6PTFIT) | C42: 2 | D42: ch | E42: 1461.22 | F42: =C42*E42 -> 2922.44 | G42: Modèle exact S1R6PTFIT à confirmer
A43: HUBHBL1372 | B43: HUBBELL HBL1372 SECTIONNEUR 30A 2P (HUM-1/2/3) | C43: 3 | D43: ch | E43: 117.84 | F43: =C43*E43 -> 353.52 | G43: Devis 20 : service intensif — à valider
A44: QUINCAILLERIE / COUPE-FEU
A45: TROCP25WB+10.1OZ | B45: 3M CP25WB+ COUPE-FEU TUBE 10,1 OZ | C45: 25 | D45: ch | E45: 26.22 | F45: =C45*E45 -> 655.5 | G45: 23 percements + extras
A46: VISTF3/8 | B46: ABB TIGE FILETÉE 3/8 PO | C46: 200 | D46: pi | E46: 0.6435 | F46: =C46*E46 -> 128.7 | G46: Suspension luminaires à la dalle (devis 16.5)
A47: VISDIA3/816BX50 | B47: USCAN ANCRAGE DROP-IN 3/8-16 (pqt 50) | C47: 2 | D47: pk | E47: 32.26 | F47: =C47*E47 -> 64.52
A48: IDE30452 | B48: IDEAL 30-452 MARRETTES (paquet) | C48: 3 | D48: pk | E48: 40.69 | F48: =C48*E48 -> 122.07
E49: TOTAL | F49: =SUM(F6:F48) -> 23159.671
